BlueWhale3_Associate-1.1.81-py3.8-nspkg.pth
orangecontrib/associate/__init__.py
orangecontrib/associate/_fpgrowth.cpp
orangecontrib/associate/_fpgrowth.cpython-38-darwin.so
orangecontrib/associate/_fpgrowth.pyx
orangecontrib/associate/fpgrowth.py
orangecontrib/associate/i18n_config.py
orangecontrib/associate/locale/associate.en.yml
orangecontrib/associate/locale/associate.zh.yml
orangecontrib/associate/widgets/__init__.py
orangecontrib/associate/widgets/owassociate.py
orangecontrib/associate/widgets/owitemsets.py
orangecontrib/associate/widgets/icons/AssociationRules.svg
orangecontrib/associate/widgets/icons/FrequentItemsets.svg
orangecontrib/associate/widgets/tests/__init__.py
orangecontrib/associate/widgets/tests/test_owassociate.py
orangecontrib/associate/widgets/tests/data/market-basket.tab
orangecontrib/associate/widgets/tests/data/test_owitemsets.py
BlueWhale3_Associate-1.1.81.dist-info/LICENSE
BlueWhale3_Associate-1.1.81.dist-info/METADATA
BlueWhale3_Associate-1.1.81.dist-info/WHEEL
BlueWhale3_Associate-1.1.81.dist-info/entry_points.txt
BlueWhale3_Associate-1.1.81.dist-info/namespace_packages.txt
BlueWhale3_Associate-1.1.81.dist-info/top_level.txt
BlueWhale3_Associate-1.1.81.dist-info/RECORD
